dawarich_api/__init__.py
dawarich_api/api_calls.py
dawarich_api/constants.py
dawarich_api/response_model.py
dawarich_api-0.4.1.dist-info/licenses/LICENSE
dawarich_api-0.4.1.dist-info/METADATA
dawarich_api-0.4.1.dist-info/WHEEL
dawarich_api-0.4.1.dist-info/top_level.txt
dawarich_api-0.4.1.dist-info/RECORD
