Metadata-Version: 2.4
Name: dawarich-api
Version: 0.4.1
Summary: A python wrapper for the Dawarich API
Author-email: Albin Lindqvist <albin.lindqvist@hotmail.se>
License:                     GNU AFFERO GENERAL PUBLIC LICENSE
Project-URL: Homepage, https://github.com/AlbinLind/dawarich-api
Project-URL: Repository, https://github.com/AlbinLind/dawarich-api
Project-URL: Dawarich, https://dawarich.app
Classifier: Operating System :: OS Independent
Requires-Python: >=3.10
License-File: LICENSE
Requires-Dist: pydantic>=2.0
Requires-Dist: aiohttp>=3.10
Provides-Extra: test
Requires-Dist: pytest>=8.3.4; extra == "test"
Requires-Dist: pytest-asyncio>=0.25.0; extra == "test"
Provides-Extra: format
Requires-Dist: ruff>=0.7.1; extra == "format"
Dynamic: license-file
